web_console/__init__.py
web_console/web/index.html
web_console/web/images/terminal.png
web_console/web/scripts/main.js
web_console/web/scripts/tree.js
web_console/web/styles/console.css
web_console/web/styles/tree.css
web_console_log-0.1.0.dist-info/METADATA
web_console_log-0.1.0.dist-info/WHEEL
web_console_log-0.1.0.dist-info/top_level.txt
web_console_log-0.1.0.dist-info/RECORD
