Metadata-Version: 2.1
Name: web_console_log
Version: 0.1.0
Summary: Python Web Console
Home-page: https://github.com/SuperZombi/Web-Console
Author: Super_Zombi
Author-email: super.zombi.yt@gmail.com
Classifier: Programming Language :: Python :: 3
Classifier: License :: OSI Approved :: MIT License
Classifier: Operating System :: OS Independent
Requires-Python: >=3.9
Requires-Dist: eventlet
Requires-Dist: python-socketio
